gym_cellular/__init__.py
gym_cellular/agent/planner.py
gym_cellular/cellular/automaton.py
gym_cellular/cellular/forest_fire.py
gym_cellular/cellular/game_of_life.py
gym_cellular/environment/env.py
gym_cellular/environment/helicopter_env.py
gym_cellular/register.py
gym_cellular-0.1.0.dist-info/LICENSE
gym_cellular-0.1.0.dist-info/METADATA
gym_cellular-0.1.0.dist-info/WHEEL
gym_cellular-0.1.0.dist-info/entry_points.txt
gym_cellular-0.1.0.dist-info/RECORD
